{
  "character": {
    "value": [
      {"title": "Name", "value": "Thaldrin Ironheart"},
      {"title": "Race", "value": "Dwarf"},
      {"title": "Class", "value": "Fighter"},
      {"title": "Level", "value": 5},
      {"title": "Background", "value": "Guild Artisan"},
      {"title": "Alignment", "value": "Lawful Good"},
      {"title": "Strength", "value": 16},
      {"title": "Dexterity", "value": 12},
      {"title": "Constitution", "value": 16},
      {"title": "Intelligence", "value": 10},
      {"title": "Wisdom", "value": 10},
      {"title": "Charisma", "value": 8},
      {"title": "Hit Points", "value": 45},
      {"title": "Armor Class", "value": 18},
      {"title": "Speed", "value": 25},
      {"title": "Proficiencies", "value": [
        "Smith's Tools",
        "Battleaxe",
        "Handaxe",
        "Throwing Hammer",
        "Light Armor",
        "Medium Armor",
        "Shields"
      ]},
      {"title": "Languages", "value": [
        "Common",
        "Dwarvish"
      ]},
      {"title": "Equipment", "value": [
        "Battleaxe",
        "Chain Mail",
        "Shield",
        "Explorer's Pack",
        "Smith's Tools",
        "Insignia of his Guild",
        "Traveler's Clothes"
      ]},
      {"title": "Features and Traits", "value": [
        "Dwarven Resilience",
        "Dwarven Combat Training",
        "Tool Proficiency: Smith's Tools",
        "Guild Membership (Guild Artisan)"
      ]},
      {"title": "Personality Traits", "value": "I always have a plan for what to do when things go wrong."},
      {"title": "Ideals", "value": "Fairness. We all do the work, so we all share in the rewards."},
      {"title": "Bonds", "value": "My guild is the most important thing in my life, even when they are far from me."},
      {"title": "Flaws", "value": "I have a hard time trusting in my allies."}
    ]
  }
}
